pyagentspec-26.1.0.dist-info/RECORD
pyagentspec-26.1.0.dist-info/LICENSE-UPL.txt
pyagentspec-26.1.0.dist-info/LICENSE-APACHE.txt
pyagentspec-26.1.0.dist-info/THIRD_PARTY_LICENSES.txt
pyagentspec-26.1.0.dist-info/WHEEL
pyagentspec-26.1.0.dist-info/top_level.txt
pyagentspec-26.1.0.dist-info/METADATA
pyagentspec/swarm.py
pyagentspec/validation_helpers.py
pyagentspec/managerworkers.py
pyagentspec/LICENSE-UPL.txt
pyagentspec/_lazy_loader.py
pyagentspec/templating.py
pyagentspec/property.py
pyagentspec/LICENSE-APACHE.txt
pyagentspec/agenticcomponent.py
pyagentspec/a2aagent.py
pyagentspec/THIRD_PARTY_LICENSES.txt
pyagentspec/__init__.py
pyagentspec/ociagent.py
pyagentspec/_openaiagent.py
pyagentspec/versioning.py
pyagentspec/remoteagent.py
pyagentspec/agent.py
pyagentspec/py.typed
pyagentspec/_component_registry.py
pyagentspec/component.py
pyagentspec/sensitive_field.py
pyagentspec/specialized_agent.py
pyagentspec/_utils.py
pyagentspec/tracing/trace.py
pyagentspec/tracing/_basemodel.py
pyagentspec/tracing/spanprocessor.py
pyagentspec/tracing/__init__.py
pyagentspec/tracing/messages/__init__.py
pyagentspec/tracing/messages/message.py
pyagentspec/tracing/spans/swarm.py
pyagentspec/tracing/spans/managerworkers.py
pyagentspec/tracing/spans/__init__.py
pyagentspec/tracing/spans/flow.py
pyagentspec/tracing/spans/llm.py
pyagentspec/tracing/spans/agent.py
pyagentspec/tracing/spans/node.py
pyagentspec/tracing/spans/root.py
pyagentspec/tracing/spans/span.py
pyagentspec/tracing/spans/tool.py
pyagentspec/tracing/events/swarm.py
pyagentspec/tracing/events/exception.py
pyagentspec/tracing/events/event.py
pyagentspec/tracing/events/managerworkers.py
pyagentspec/tracing/events/__init__.py
pyagentspec/tracing/events/flow.py
pyagentspec/tracing/events/humanintheloop.py
pyagentspec/tracing/events/llmgeneration.py
pyagentspec/tracing/events/agent.py
pyagentspec/tracing/events/node.py
pyagentspec/tracing/events/tool.py
pyagentspec/tools/servertool.py
pyagentspec/tools/toolbox.py
pyagentspec/tools/clienttool.py
pyagentspec/tools/__init__.py
pyagentspec/tools/remotetool.py
pyagentspec/tools/tool.py
pyagentspec/tools/builtintool.py
pyagentspec/serialization/builtinsdeserializationplugin.py
pyagentspec/serialization/deserializer.py
pyagentspec/serialization/pydanticserializationplugin.py
