Metadata-Version: 2.1
Name: pyagentspec
Version: 26.1.0
Summary: Package defining the PyAgentSpec library for Agents and LLM fixed-flows abstractions.
Home-page: https://github.com/oracle/agent-spec
Author: Oracle
Author-email: 
License: Apache-2.0 OR UPL-1.0
Keywords: NLP,text generation,code generation,LLM,Assistant,Tool,Agent
Classifier: Development Status :: 3 - Alpha
Classifier: Natural Language :: English
Classifier: Intended Audience :: Science/Research
Classifier: Programming Language :: Python
Classifier: Programming Language :: Python :: 3.10
Classifier: Programming Language :: Python :: 3.11
Classifier: Programming Language :: Python :: 3.12
Classifier: Programming Language :: Python :: 3.13
Classifier: Programming Language :: Python :: 3.14
Classifier: Topic :: Software Development :: Libraries :: Python Modules
Requires-Python: >=3.10
Requires-Dist: jsonschema<5,>=4.23.0
Requires-Dist: pydantic<2.13,>=2.10
Requires-Dist: pyyaml<7,>=6
Requires-Dist: httpx>0.28.0
Requires-Dist: urllib3>=2.5.0
Provides-Extra: autogen
Requires-Dist: autogen-core>=0.5.6; python_version < "3.13" and extra == "autogen"
Requires-Dist: autogen-ext[ollama,openai]>=0.5.6; python_version < "3.13" and extra == "autogen"
Requires-Dist: autogen-agentchat>=0.5.6; python_version < "3.13" and extra == "autogen"
Provides-Extra: langgraph
Requires-Dist: langgraph<1.0.0,>=0.5.3; extra == "langgraph"
Requires-Dist: langchain-core<1.0.0,>=0.3; extra == "langgraph"
Requires-Dist: langchain-openai>=0.3.7; extra == "langgraph"
Requires-Dist: langchain-ollama>=0.3.3; extra == "langgraph"
Requires-Dist: langgraph-checkpoint<4.0.0,>=3.0.1; extra == "langgraph"
Requires-Dist: anyio<4.12.0,>=4.10.0; extra == "langgraph"
Provides-Extra: langgraph_mcp
Requires-Dist: langgraph<1.0.0,>=0.5.3; extra == "langgraph-mcp"
Requires-Dist: langchain-core<1.0.0,>=0.3; extra == "langgraph-mcp"
Requires-Dist: langchain-openai>=0.3.7; extra == "langgraph-mcp"
Requires-Dist: langchain-ollama>=0.3.3; extra == "langgraph-mcp"
Requires-Dist: langgraph-checkpoint<4.0.0,>=3.0.1; extra == "langgraph-mcp"
Requires-Dist: anyio<4.12.0,>=4.10.0; extra == "langgraph-mcp"
Requires-Dist: langchain-mcp-adapters<0.2.0,>=0.1.13; extra == "langgraph-mcp"
License-File: THIRD_PARTY_LICENSES.txt
License-File: LICENSE-APACHE.txt
License-File: LICENSE-UPL.txt
